cloud/__init__.py
cloud/__version__.py
cloud/main.py
wonderbitscloud/__init__.py
wonderbitscloud/__version__.py
wonderbitscloud/main.py
wonderbitscloud-0.2.2.dist-info/LICENSE
wonderbitscloud-0.2.2.dist-info/METADATA
wonderbitscloud-0.2.2.dist-info/WHEEL
wonderbitscloud-0.2.2.dist-info/top_level.txt
wonderbitscloud-0.2.2.dist-info/RECORD
