Metadata-Version: 2.1
Name: wonderbitscloud
Version: 0.2.2
Summary: wonderbitscloud allows you to use variables remotely.
Home-page: UNKNOWN
Author: mfe
Author-email: account@mfeducation.cn
Maintainer: mfe
Maintainer-email: account@mfeducation.cn
License: MIT License
Platform: all
Classifier: License :: OSI Approved :: MIT License
Classifier: Programming Language :: Python :: 3
